gretel_synthetics/__init__.py
gretel_synthetics/batch.py
gretel_synthetics/config.py
gretel_synthetics/const.py
gretel_synthetics/errors.py
gretel_synthetics/generate.py
gretel_synthetics/generate_parallel.py
gretel_synthetics/generate_utils.py
gretel_synthetics/tokenizers.py
gretel_synthetics/train.py
gretel_synthetics/typing.py
gretel_synthetics/actgan/__init__.py
gretel_synthetics/actgan/actgan.py
gretel_synthetics/actgan/actgan_wrapper.py
gretel_synthetics/actgan/base.py
gretel_synthetics/actgan/column_encodings.py
gretel_synthetics/actgan/columnar_df.py
gretel_synthetics/actgan/data_sampler.py
gretel_synthetics/actgan/data_transformer.py
gretel_synthetics/actgan/structures.py
gretel_synthetics/actgan/train_data.py
gretel_synthetics/actgan/transformers.py
gretel_synthetics/detectors/__init__.py
gretel_synthetics/detectors/dates.py
gretel_synthetics/detectors/sdv.py
gretel_synthetics/timeseries_dgan/__init__.py
gretel_synthetics/timeseries_dgan/config.py
gretel_synthetics/timeseries_dgan/dgan.py
gretel_synthetics/timeseries_dgan/structures.py
gretel_synthetics/timeseries_dgan/torch_modules.py
gretel_synthetics/timeseries_dgan/transformations.py
gretel_synthetics/utils/__init__.py
gretel_synthetics/utils/data.py
gretel_synthetics/utils/header_clusters.py
gretel_synthetics/utils/rdt_patches.py
gretel_synthetics/utils/stats.py
gretel_synthetics/utils/tar_util.py
gretel_synthetics/utils/torch_utils.py
gretel_synthetics-0.22.20.dist-info/LICENSE
gretel_synthetics-0.22.20.dist-info/METADATA
gretel_synthetics-0.22.20.dist-info/WHEEL
gretel_synthetics-0.22.20.dist-info/top_level.txt
gretel_synthetics-0.22.20.dist-info/RECORD
