Metadata-Version: 2.1
Name: gretel-synthetics
Version: 0.22.20
Summary: Synthetic Data Generation with optional Differential Privacy
Home-page: https://github.com/gretelai/gretel-synthetics
Author: Gretel Labs, Inc.
Author-email: support@gretel.ai
License: https://gretel.ai/license/source-available-license
Platform: UNKNOWN
Classifier: Programming Language :: Python :: 3
Classifier: License :: Free To Use But Restricted
Classifier: Operating System :: POSIX :: Linux
Classifier: Operating System :: MacOS
Classifier: Operating System :: Microsoft :: Windows
Classifier: Topic :: Scientific/Engineering :: Artificial Intelligence
Requires-Python: >=3.9
License-File: LICENSE
Requires-Dist: category-encoders==2.4.0
Requires-Dist: numpy<1.24,>=1.18.0
Requires-Dist: pandas<2,>=1.1.0
Requires-Dist: protobuf<=4.24.0,>=4
Requires-Dist: rdt<1.3,>=1.2
Requires-Dist: sdv<0.18,>=0.17
Requires-Dist: sentencepiece==0.2.0
Requires-Dist: tqdm<5.0,>=4.66
Provides-Extra: all
Requires-Dist: category-encoders==2.4.0; extra == "all"
Requires-Dist: numpy<1.24,>=1.18.0; extra == "all"
Requires-Dist: pandas<2,>=1.1.0; extra == "all"
Requires-Dist: protobuf<=4.24.0,>=4; extra == "all"
Requires-Dist: rdt<1.3,>=1.2; extra == "all"
Requires-Dist: sdv<0.18,>=0.17; extra == "all"
Requires-Dist: sentencepiece==0.2.0; extra == "all"
Requires-Dist: tqdm<5.0,>=4.66; extra == "all"
Requires-Dist: dython==0.7.0; extra == "all"
Requires-Dist: scikit-learn>=0.24; extra == "all"
Requires-Dist: scipy<1.11,>=1.4.1; extra == "all"
Requires-Dist: torch>=1.13; extra == "all"
Provides-Extra: docs
Requires-Dist: docutils==0.18.1; extra == "docs"
Requires-Dist: jinja2==3.1.6; extra == "docs"
Requires-Dist: m2r==0.3.1; extra == "docs"
Requires-Dist: mistune==0.8.4; extra == "docs"
Requires-Dist: sphinx-rtd-theme==1.2.2; extra == "docs"
Requires-Dist: sphinx==6.2.1; extra == "docs"
Provides-Extra: test
Requires-Dist: faker==20.1.0; extra == "test"
Requires-Dist: flake8==4.0.1; extra == "test"
Requires-Dist: pylint==3.3.1; extra == "test"
Requires-Dist: pytest-cov==2.11.1; extra == "test"
Requires-Dist: pytest==7.2.0; extra == "test"
Requires-Dist: requests==2.32.2; extra == "test"
Requires-Dist: smart-open<8.0,>=2.1.0; extra == "test"
Provides-Extra: torch
Requires-Dist: torch>=1.13; extra == "torch"
Provides-Extra: utils
Requires-Dist: dython==0.7.0; extra == "utils"
Requires-Dist: scikit-learn>=0.24; extra == "utils"
Requires-Dist: scipy<1.11,>=1.4.1; extra == "utils"
